fifo/fifo.sv
module fifo #(parameter DATA_WIDTH = 4, parameter DEPTH = 8) (
    input                       clk,
    input                       rst,

    input                       wr,
    input                       rd, 

    input           [DATA_WIDTH-1:0]    data_in,
    output logic    [DATA_WIDTH-1:0]    data_out,

    output                      full,
    output                      empty

    
);

localparam ADDR_WIDTH = $clog2(DEPTH);

logic   [DATA_WIDTH-1:0]    mem [DEPTH-1:0];
logic   [ADDR_WIDTH-1:0]    wr_addr;
logic   [ADDR_WIDTH-1:0]    rd_addr;

always @(posedge clk or posedge rst) begin
    if(rst) begin
        wr_addr     <= '0;
        rd_addr     <= '0;
        data_out    <= '0;
    end else begin
        if(wr & rd) begin
            mem[wr_addr]    <= data_in;
            data_out        <= mem[rd_addr];
        end else if(wr & !full) begin
            wr_addr         <= (wr_addr < DEPTH-1) ? wr_addr + 1 : '0;
            mem[wr_addr]    <= data_in;
        end else if(rd & !empty) begin
            rd_addr     <= (rd_addr < DEPTH-1) ? rd_addr + 1 : '0;
            data_out    <= mem[rd_addr];
        end
    end
end

assign  full    = ({~wr_addr[ADDR_WIDTH-1], wr_addr[ADDR_WIDTH-2:0]} == rd_addr);
assign  empty   = (wr_addr == rd_addr);

endmodule

fifo/fifo_tb.sv
`include "fifo.sv"
`timescale 1ps/1ps

module fifo_tb();

    parameter                   DEPTH = 4;
    parameter                   DATA_WIDTH = 4;

    logic                       clk;
    logic                       rst;

    logic                       wr;
    logic                       rd; 

    logic           [DATA_WIDTH-1:0]    data_in;
    logic           [DATA_WIDTH-1:0]    data_out;

    logic                      full;
    logic                      empty;


    fifo #(
        .DATA_WIDTH(DATA_WIDTH),
        .DEPTH(DEPTH)
    ) dut (
        .clk(clk),
        .rst(rst),
        .wr(wr),
        .rd(rd),
        .data_in(data_in),
        .data_out(data_out),
        .full(full),
        .empty(empty)
    );

    always #5 clk = ~clk;

    logic   [DATA_WIDTH-1:0]    dut_output [$];
    logic   [DATA_WIDTH-1:0]    golden_output[$];    
    logic   [DATA_WIDTH-1:0]    rand_data;               

    task init();
        rst     = 1'b0;
        clk     = 1'b0;
        wr      = 1'b0;
        rd      = 1'b0;
        data_in = '0;

        @(posedge clk);
        rst = 1'b1;
        @(posedge clk);
        rst = 1'b0;
        @(posedge clk);
        #1;
    endtask

    task fifo_write(input logic [DATA_WIDTH-1:0] rand_data);
        wr = 1'b1;

        @(posedge clk);
        data_in = rand_data;
        if(!full) golden_output.push_back(rand_data);
        @(posedge clk);
        wr = 1'b0;
    endtask

    task fifo_read();
        rd = 1'b1;
        @(posedge clk)
        dut_output.push_back(data_out);
        rd = 1'b0;
    endtask

    initial begin
        $dumpfile("waves.vcd");
        $dumpvars(0, fifo_tb);

        init();
        
        repeat(3) begin
            rand_data = $urandom();
            fifo_write(rand_data);
            fifo_read();
        end

        repeat(3) begin
            rand_data = $urandom();
            repeat(2) fifo_write(rand_data);
            fifo_read();
        end

        if(golden_output.size() != dut_output.size()) begin
            $display("TEST FAILED: Reference data size does not match DUT output.");
            $finish();
        end
        for(int i = 0; i < golden_output.size(); i++) begin
            if(golden_output[i] != dut_output[i]) begin
                $display("TEST FAILED: Reference data does not match DUT output.");
                $finish();
            end
        end

        $display("TEST PASSED!");
        
        $finish();
    end
endmodule

fifo/waves.vcd
$date
	Wed Nov 15 17:51:31 2023
$end
$version
	Icarus Verilog
$end
$timescale
	1ps
$end
$scope module fifo_tb $end
$var wire 1 ! full $end
$var wire 1 " empty $end
$var wire 4 # data_out [3:0] $end
$var reg 1 $ clk $end
$var reg 4 % data_in [3:0] $end
$var reg 4 & rand_data [3:0] $end
$var reg 1 ' rd $end
$var reg 1 ( rst $end
$var reg 1 ) wr $end
$scope module dut $end
$var wire 1 $ clk $end
$var wire 4 * data_in [3:0] $end
$var wire 1 ' rd $end
$var wire 1 ( rst $end
$var wire 1 ) wr $end
$var wire 1 ! full $end
$var wire 1 " empty $end
$var reg 4 + data_out [3:0] $end
$var reg 2 , rd_addr [1:0] $end
$var reg 2 - wr_addr [1:0] $end
$upscope $end
$scope begin $ivl_for_loop0 $end
$var integer 32 . i [31:0] $end
$upscope $end
$scope task fifo_read $end
$upscope $end
$scope task fifo_write $end
$var reg 4 / rand_data [3:0] $end
$upscope $end
$scope task init $end
$upscope $end
$upscope $end
$enddefinitions $end
#0
$dumpvars
bx /
b0 .
bx -
bx ,
bx +
b0 *
0)
0(
0'
bx &
b0 %
0$
bx #
x"
x!
$end
#5
0!
1"
b0 ,
b0 -
1(
1$
#10
0$
#15
0(
1$
#20
0$
#25
1$
#26
1)
b100 /
b100 &
#30
0$
#35
0"
b1 -
b100 %
b100 *
1$
#40
0$
#45
b100 #
b100 +
1"
b1 ,
1'
0)
1$
#50
0$
#55
0"
b10 -
1)
b1 /
b1 &
0'
1$
#60
0$
#65
1!
b11 -
b1 %
b1 *
1$
#70
0$
#75
0!
b10 ,
1'
0)
1$
#80
0$
#85
1!
b0 -
1)
b1001 /
b1001 &
0'
1$
#90
0$
#95
b1001 %
b1001 *
1$
#100
0$
#105
b1 #
b1 +
0!
b11 ,
1'
0)
1$
#110
0$
#115
1!
b1 -
1)
b11 /
b11 &
0'
1$
#120
0$
#125
b11 %
b11 *
1$
#130
0$
#135
1)
1$
#140
0$
#145
1$
#150
0$
#155
0!
b0 ,
1'
0)
1$
#160
0$
#165
1!
b10 -
1)
b1101 /
b1101 &
0'
1$
#170
0$
#175
b1101 %
b1101 *
1$
#180
0$
#185
1)
1$
#190
0$
#195
1$
#200
0$
#205
b1001 #
b1001 +
0!
b1 ,
1'
0)
1$
#210
0$
#215
1!
b11 -
1)
0'
1$
#220
0$
#225
1$
#230
0$
#235
1)
1$
#240
0$
#245
1$
#250
0$
#255
b11 #
b11 +
0!
b10 ,
1'
0)
1$
#260
0$
#265
0'
1$
